phpserialize/__init__.py
phpserialize/decorators.py
phpserialize/php_ini.py
phpserialize/serialize.py
phpserialize/types.py
phpserialize/unserialize.py
libphpserialize-0.0.8.dist-info/METADATA
libphpserialize-0.0.8.dist-info/WHEEL
libphpserialize-0.0.8.dist-info/top_level.txt
libphpserialize-0.0.8.dist-info/RECORD
