Metadata-Version: 2.1
Name: libphpserialize
Version: 0.0.8
Summary: A port of PHP's serialize function, in pure python
Home-page: https://github.com/frankli0324/libphpserialize
Author: Frank
Author-email: frankli0324@hotmail.com
Classifier: Programming Language :: Python :: 3
Classifier: License :: OSI Approved :: MIT License
Requires-Python: >=3.7
